[{"no":"#1","sehar":"04:10 AM","iftar":"6:39 PM","date":"2021-04-14"},{"no":"#2","sehar":"04:09 AM","iftar":"6:39 PM","date":"2021-04-15"},{"no":"#3","sehar":"04:07 AM","iftar":"6:40 PM","date":"2021-04-16"},{"no":"#4","sehar":"04:06 AM","iftar":"6:41 PM","date":"2021-04-17"},{"no":"#5","sehar":"04:04 AM","iftar":"6:42 PM","date":"2021-04-18"},{"no":"#6","sehar":"04:03 AM","iftar":"6:42 PM","date":"2021-04-19"},{"no":"#7","sehar":"04:01 AM","iftar":"6:43 PM","date":"2021-04-20"},{"no":"#8","sehar":"04:00 AM","iftar":"6:44 PM","date":"2021-04-21"},{"no":"#9","sehar":"03:59 AM","iftar":"6:45 PM","date":"2021-04-22"},{"no":"#10","sehar":"03:57 AM","iftar":"6:45 PM","date":"2021-04-23"},{"no":"#11","sehar":"03:56 AM","iftar":"6:46 PM","date":"2021-04-24"},{"no":"#12","sehar":"03:54 AM","iftar":"6:47 PM","date":"2021-04-25"},{"no":"#13","sehar":"03:53 AM","iftar":"6:48 PM","date":"2021-04-26"},{"no":"#14","sehar":"03:52 AM","iftar":"6:48 PM","date":"2021-04-27"},{"no":"#15","sehar":"03:50 AM","iftar":"6:49 PM","date":"2021-04-28"},{"no":"#16","sehar":"03:49 AM","iftar":"6:50 PM","date":"2021-04-29"},{"no":"#17","sehar":"03:47 AM","iftar":"6:51 PM","date":"2021-04-30"},{"no":"#18","sehar":"03:46 AM","iftar":"6:51 PM","date":"2021-05-01"},{"no":"#19","sehar":"03:45 AM","iftar":"6:52 PM","date":"2021-05-02"},{"no":"#20","sehar":"03:44 AM","iftar":"6:53 PM","date":"2021-05-03"},{"no":"#21","sehar":"03:42 AM","iftar":"6:54 PM","date":"2021-05-04"},{"no":"#22","sehar":"03:41 AM","iftar":"6:55 PM","date":"2021-05-05"},{"no":"#23","sehar":"03:40 AM","iftar":"6:55 PM","date":"2021-05-06"},{"no":"#24","sehar":"03:39 AM","iftar":"6:56 PM","date":"2021-05-07"},{"no":"#25","sehar":"03:37 AM","iftar":"6:57 PM","date":"2021-05-08"},{"no":"#26","sehar":"03:36 AM","iftar":"6:58 PM","date":"2021-05-09"},{"no":"#27","sehar":"03:35 AM","iftar":"6:58 PM","date":"2021-05-10"},{"no":"#28","sehar":"03:34 AM","iftar":"6:59 PM","date":"2021-05-11"},{"no":"#29","sehar":"03:33 AM","iftar":"7:00 PM","date":"2021-05-12"},{"no":"#30","sehar":"03:32 AM","iftar":"7:01 PM","date":"2021-05-13"}]